MANIFEST.in
README.rst
requirements.txt
setup.py
python_sdcclient.egg-info/PKG-INFO
python_sdcclient.egg-info/SOURCES.txt
python_sdcclient.egg-info/dependency_links.txt
python_sdcclient.egg-info/requires.txt
python_sdcclient.egg-info/top_level.txt
sdcclient/__init__.py
sdcclient/client.py
sdcclient/productandrelease_resource_client.py
sdcclient/utils/__init__.py
sdcclient/utils/logger_utils.py
sdcclient/utils/rest_client_utils.py