Metadata-Version: 1.0
Name: python-sdcclient
Version: 0.0.8
Summary: SDC Client
Home-page: https://github.com/telefonicaid/fiware-sdc/python-sdcclient
Author: jmms39
Author-email: UNKNOWN
License: UNKNOWN
Platform: UNKNOWN
